auth/__init__.py
auth/main.py
auth/cmd/__init__.py
auth/cmd/add.py
auth/cmd/add_qr.py
auth/cmd/gen.py
auth/cmd/list.py
auth/cmd/remove.py
auth/utils/__init__.py
auth/utils/params.py
auth/utils/utils.py
auth_cmd-0.4.dist-info/LICENSE
auth_cmd-0.4.dist-info/METADATA
auth_cmd-0.4.dist-info/WHEEL
auth_cmd-0.4.dist-info/entry_points.txt
auth_cmd-0.4.dist-info/top_level.txt
auth_cmd-0.4.dist-info/RECORD
