Metadata-Version: 2.1
Name: auth-cmd
Version: 0.4
Summary: A 2FA/TOTP authentication tool
Home-page: https://github.com/KaiChen1008/auth-cmd
Author: Ken Lin
Classifier: Development Status :: 4 - Beta
Classifier: Environment :: Console
Classifier: Intended Audience :: Developers
Classifier: Programming Language :: Python :: 3
Classifier: License :: OSI Approved :: MIT License
Classifier: Operating System :: OS Independent
Requires-Python: >=3.6
License-File: LICENSE
Requires-Dist: click
Requires-Dist: regex
Requires-Dist: typing
Requires-Dist: pathlib
Requires-Dist: pyzbar
Requires-Dist: pillow
Requires-Dist: pyperclip
Requires-Dist: pybase64
